{
    "@context": "http://iiif.io/api/presentation/2/context.json",
    "@id": "https://nakamura196.github.io/lda2/metro/manifest/6da1d85c5d015c1206ec41f637dd3c98.json",
    "@type": "sc:Manifest",
    "attribution": "TOKYOアーカイブ",
    "label": "帝室京都博物館所蔵春日厨子などのスケッチ",
    "license": "http://archive.library.metro.tokyo.jp/da/windowTokyo",
    "metadata": [
        {
            "label": "カテゴリ",
            "value": "/建築図面"
        },
        {
            "label": "分類",
            "value": "清逸すけっち集/清逸すけっち雑集///"
        },
        {
            "label": "大きさ（cm）",
            "value": "15.5×10、15.5×10、台紙27.5×39.5cm"
        },
        {
            "label": "文庫名",
            "value": "木子文庫"
        },
        {
            "label": "製作者",
            "value": "東京都立図書館"
        },
        {
            "label": "請求記号",
            "value": "木163-4-76/木163-4-076"
        },
        {
            "label": "題名",
            "value": "帝室京都博物館所蔵春日厨子などのスケッチ"
        },
        {
            "label": "題名",
            "value": "テイシツ　キョウト　ハクブツカン　ショゾウ　カスガズシ　ナド　ノ　スケッチ"
        },
        {
            "label": "体裁",
            "value": "図面"
        },
        {
            "label": "作成年",
            "value": "［昭和初期］"
        },
        {
            "label": "家名・人名",
            "value": "木子幸三郎"
        },
        {
            "label": "数量",
            "value": "２枚"
        },
        {
            "label": "内容等",
            "value": "スケッチ"
        }
    ],
    "related": "http://archive.library.metro.tokyo.jp/da/detail?tilcod=0000000016-00075944",
    "sequences": [
        {
            "@id": "https://nakamura196.github.io/lda2/metro/manifest/6da1d85c5d015c1206ec41f637dd3c98.json/sequence/normal",
            "@type": "sc:Sequence",
            "canvases": [
                {
                    "@id": "https://nakamura196.github.io/lda2/metro/manifest/6da1d85c5d015c1206ec41f637dd3c98.json/canvas/p1",
                    "@type": "sc:Canvas",
                    "height": 4500,
                    "images": [
                        {
                            "@id": "https://nakamura196.github.io/lda2/metro/manifest/6da1d85c5d015c1206ec41f637dd3c98.json/annotation/p1-image",
                            "@type": "oa:Annotation",
                            "motivation": "sc:painting",
                            "on": "https://nakamura196.github.io/lda2/metro/manifest/6da1d85c5d015c1206ec41f637dd3c98.json/canvas/p1",
                            "resource": {
                                "@id": "http://archive.library.metro.tokyo.jp/da/download/?id=0000000016-00075944&size=org&type=image&file=%2F%E5%BB%BA%E7%AF%89%E5%9B%B3%E9%9D%A2%2FKI163-004-076.jpg",
                                "@type": "dctypes:Image",
                                "format": "image/jpeg",
                                "height": 4500,
                                "width": 6000
                            }
                        }
                    ],
                    "label": "[1]",
                    "thumbnail": {
                        "@id": "http://archive.library.metro.tokyo.jp/da/download/?id=0000000016-00075944&size=thumb&type=image&file=%2F%E5%BB%BA%E7%AF%89%E5%9B%B3%E9%9D%A2%2FKI163-004-076.jpg"
                    },
                    "width": 6000
                }
            ],
            "label": "Current Page Order",
            "viewingHint": "non-paged"
        }
    ],
    "thumbnail": {
        "@id": "http://archive.library.metro.tokyo.jp/da/download/?id=0000000016-00075944&size=thumb&type=image&file=%2F%E5%BB%BA%E7%AF%89%E5%9B%B3%E9%9D%A2%2FKI163-004-076.jpg"
    },
    "within": "http://archive.library.metro.tokyo.jp/da/top"
}