{
    "@context": "http://iiif.io/api/presentation/2/context.json",
    "@id": "https://nakamura196.github.io/lda2/metro/manifest/de06d08fed0d224898b390213807d34c.json",
    "@type": "sc:Manifest",
    "attribution": "TOKYOアーカイブ",
    "label": "[タイトルなし]",
    "license": "http://archive.library.metro.tokyo.jp/da/windowTokyo",
    "metadata": [
        {
            "label": "カテゴリ",
            "value": "/浮世絵"
        },
        {
            "label": "出版年",
            "value": "文政末"
        },
        {
            "label": "分類",
            "value": "////"
        },
        {
            "label": "文庫名",
            "value": "加賀文庫"
        },
        {
            "label": "書誌注記",
            "value": "；錦絵の貼込帖，「江戸錦繪帖」所収；；；；；；；；；；｜//////////////｜/"
        },
        {
            "label": "製作者",
            "value": "東京都立図書館"
        },
        {
            "label": "請求記号",
            "value": "加4647-(裏39）/加04647-(裏039）"
        },
        {
            "label": "出版地",
            "value": "大坂"
        },
        {
            "label": "画中文字",
            "value": "「大阪天満宮祭礼之図」"
        },
        {
            "label": "件名",
            "value": "岳亭春信（ガクテイ　ハルノブ）（生没年未詳）"
        },
        {
            "label": "浮世絵種別",
            "value": "その他の浮世絵"
        },
        {
            "label": "版種",
            "value": "大判/錦絵/横"
        },
        {
            "label": "画題等",
            "value": "「大阪天満宮祭礼之図」"
        },
        {
            "label": "画題等",
            "value": "オオサカ　テンマングウ　サイレイ　ノ　ズ"
        },
        {
            "label": "絵師・落款",
            "value": "岳亭春信"
        },
        {
            "label": "絵師・落款",
            "value": ""
        },
        {
            "label": "絵師・落款",
            "value": "筆"
        },
        {
            "label": "絵師・落款",
            "value": "五岳筆"
        }
    ],
    "related": "http://archive.library.metro.tokyo.jp/da/detail?tilcod=0000000003-00019485",
    "sequences": [
        {
            "@id": "https://nakamura196.github.io/lda2/metro/manifest/de06d08fed0d224898b390213807d34c.json/sequence/normal",
            "@type": "sc:Sequence",
            "canvases": [
                {
                    "@id": "https://nakamura196.github.io/lda2/metro/manifest/de06d08fed0d224898b390213807d34c.json/canvas/p1",
                    "@type": "sc:Canvas",
                    "height": 1107,
                    "images": [
                        {
                            "@id": "https://nakamura196.github.io/lda2/metro/manifest/de06d08fed0d224898b390213807d34c.json/annotation/p1-image",
                            "@type": "oa:Annotation",
                            "motivation": "sc:painting",
                            "on": "https://nakamura196.github.io/lda2/metro/manifest/de06d08fed0d224898b390213807d34c.json/canvas/p1",
                            "resource": {
                                "@id": "http://archive.library.metro.tokyo.jp/da/download?id=0000000003-00019485&size=org&type=image&file=%2F%E6%B5%AE%E4%B8%96%E7%B5%B5%2FKA4647-Y39.jpg",
                                "@type": "dctypes:Image",
                                "format": "image/jpeg",
                                "height": 1107,
                                "width": 1656
                            }
                        }
                    ],
                    "label": "[1]",
                    "thumbnail": {
                        "@id": "http://archive.library.metro.tokyo.jp/da/download?id=0000000003-00019485&size=thumb&type=image&file=%2F%E6%B5%AE%E4%B8%96%E7%B5%B5%2FKA4647-Y39.jpg"
                    },
                    "width": 1656
                }
            ],
            "label": "Current Page Order",
            "viewingHint": "non-paged"
        }
    ],
    "thumbnail": {
        "@id": "http://archive.library.metro.tokyo.jp/da/download?id=0000000003-00019485&size=thumb&type=image&file=%2F%E6%B5%AE%E4%B8%96%E7%B5%B5%2FKA4647-Y39.jpg"
    },
    "within": "http://archive.library.metro.tokyo.jp/da/top"
}