{
    "@context": "http://iiif.io/api/presentation/2/context.json",
    "@id": "https://nakamura196.github.io/lda2/nagano/manifest/de56bd4685a8d622809972830d673956.json",
    "@type": "sc:Manifest",
    "attribution": "県立長野図書館",
    "label": "火之元旅人詮義請連判",
    "license": "http://creativecommons.org/publicdomain/mark/1.0/",
    "metadata": [
        {
            "label": "分野",
            "value": "歴史"
        },
        {
            "label": "制作年（和暦）",
            "value": "宝暦11年"
        },
        {
            "label": "施設名",
            "value": "県立長野図書館"
        },
        {
            "label": "資料コード",
            "value": "02OD5020070000"
        },
        {
            "label": "資料解説",
            "value": "宝暦11年（1761）9月、幕府から出された触の請書連判帳である。近年宿場の火事が多い。自今風はげしいときは、番人を増やし灰小屋までも注意すること、出火の届は家数・長さなどを届け出ること、大雨で脇道を通行するときには絵図を添えて届け出ること、旅人は身元を糺し怪しい者を泊めないことなどを指図している。西柏原村145人の連印がある。"
        },
        {
            "label": "制作年（西暦）",
            "value": "1761年"
        },
        {
            "label": "時代",
            "value": "江戸"
        }
    ],
    "related": "http://www.i-repository.net/il/meta_pub/G0000307library_02OD5020070000",
    "sequences": [
        {
            "@id": "https://nakamura196.github.io/lda2/nagano/manifest/de56bd4685a8d622809972830d673956.json/sequence/normal",
            "@type": "sc:Sequence",
            "canvases": [
                {
                    "@id": "https://nakamura196.github.io/lda2/nagano/manifest/de56bd4685a8d622809972830d673956.json/canvas/p1",
                    "@type": "sc:Canvas",
                    "height": 2016,
                    "images": [
                        {
                            "@id": "https://nakamura196.github.io/lda2/nagano/manifest/de56bd4685a8d622809972830d673956.json/annotation/p1-image",
                            "@type": "oa:Annotation",
                            "motivation": "sc:painting",
                            "on": "https://nakamura196.github.io/lda2/nagano/manifest/de56bd4685a8d622809972830d673956.json/canvas/p1",
                            "resource": {
                                "@id": "http://www.i-repository.net/il/cont/01/G0000307library/000/148/000148967.jpg",
                                "@type": "dctypes:Image",
                                "format": "image/jpeg",
                                "height": 2016,
                                "width": 3024
                            }
                        }
                    ],
                    "label": "[1]",
                    "thumbnail": {
                        "@id": "http://www.i-repository.net/il/cont/01/G0000307library/000/148/000148967_ls.jpg"
                    },
                    "width": 3024
                },
                {
                    "@id": "https://nakamura196.github.io/lda2/nagano/manifest/de56bd4685a8d622809972830d673956.json/canvas/p2",
                    "@type": "sc:Canvas",
                    "height": 2016,
                    "images": [
                        {
                            "@id": "https://nakamura196.github.io/lda2/nagano/manifest/de56bd4685a8d622809972830d673956.json/annotation/p2-image",
                            "@type": "oa:Annotation",
                            "motivation": "sc:painting",
                            "on": "https://nakamura196.github.io/lda2/nagano/manifest/de56bd4685a8d622809972830d673956.json/canvas/p2",
                            "resource": {
                                "@id": "http://www.i-repository.net/il/cont/01/G0000307library/000/148/000148969.jpg",
                                "@type": "dctypes:Image",
                                "format": "image/jpeg",
                                "height": 2016,
                                "width": 3024
                            }
                        }
                    ],
                    "label": "[2]",
                    "thumbnail": {
                        "@id": "http://www.i-repository.net/il/cont/01/G0000307library/000/148/000148969_ls.jpg"
                    },
                    "width": 3024
                },
                {
                    "@id": "https://nakamura196.github.io/lda2/nagano/manifest/de56bd4685a8d622809972830d673956.json/canvas/p3",
                    "@type": "sc:Canvas",
                    "height": 2016,
                    "images": [
                        {
                            "@id": "https://nakamura196.github.io/lda2/nagano/manifest/de56bd4685a8d622809972830d673956.json/annotation/p3-image",
                            "@type": "oa:Annotation",
                            "motivation": "sc:painting",
                            "on": "https://nakamura196.github.io/lda2/nagano/manifest/de56bd4685a8d622809972830d673956.json/canvas/p3",
                            "resource": {
                                "@id": "http://www.i-repository.net/il/cont/01/G0000307library/000/148/000148978.jpg",
                                "@type": "dctypes:Image",
                                "format": "image/jpeg",
                                "height": 2016,
                                "width": 3024
                            }
                        }
                    ],
                    "label": "[3]",
                    "thumbnail": {
                        "@id": "http://www.i-repository.net/il/cont/01/G0000307library/000/148/000148978_ls.jpg"
                    },
                    "width": 3024
                },
                {
                    "@id": "https://nakamura196.github.io/lda2/nagano/manifest/de56bd4685a8d622809972830d673956.json/canvas/p4",
                    "@type": "sc:Canvas",
                    "height": 2016,
                    "images": [
                        {
                            "@id": "https://nakamura196.github.io/lda2/nagano/manifest/de56bd4685a8d622809972830d673956.json/annotation/p4-image",
                            "@type": "oa:Annotation",
                            "motivation": "sc:painting",
                            "on": "https://nakamura196.github.io/lda2/nagano/manifest/de56bd4685a8d622809972830d673956.json/canvas/p4",
                            "resource": {
                                "@id": "http://www.i-repository.net/il/cont/01/G0000307library/000/148/000148981.jpg",
                                "@type": "dctypes:Image",
                                "format": "image/jpeg",
                                "height": 2016,
                                "width": 3024
                            }
                        }
                    ],
                    "label": "[4]",
                    "thumbnail": {
                        "@id": "http://www.i-repository.net/il/cont/01/G0000307library/000/148/000148981_ls.jpg"
                    },
                    "width": 3024
                },
                {
                    "@id": "https://nakamura196.github.io/lda2/nagano/manifest/de56bd4685a8d622809972830d673956.json/canvas/p5",
                    "@type": "sc:Canvas",
                    "height": 2016,
                    "images": [
                        {
                            "@id": "https://nakamura196.github.io/lda2/nagano/manifest/de56bd4685a8d622809972830d673956.json/annotation/p5-image",
                            "@type": "oa:Annotation",
                            "motivation": "sc:painting",
                            "on": "https://nakamura196.github.io/lda2/nagano/manifest/de56bd4685a8d622809972830d673956.json/canvas/p5",
                            "resource": {
                                "@id": "http://www.i-repository.net/il/cont/01/G0000307library/000/148/000148982.jpg",
                                "@type": "dctypes:Image",
                                "format": "image/jpeg",
                                "height": 2016,
                                "width": 3024
                            }
                        }
                    ],
                    "label": "[5]",
                    "thumbnail": {
                        "@id": "http://www.i-repository.net/il/cont/01/G0000307library/000/148/000148982_ls.jpg"
                    },
                    "width": 3024
                },
                {
                    "@id": "https://nakamura196.github.io/lda2/nagano/manifest/de56bd4685a8d622809972830d673956.json/canvas/p6",
                    "@type": "sc:Canvas",
                    "height": 2016,
                    "images": [
                        {
                            "@id": "https://nakamura196.github.io/lda2/nagano/manifest/de56bd4685a8d622809972830d673956.json/annotation/p6-image",
                            "@type": "oa:Annotation",
                            "motivation": "sc:painting",
                            "on": "https://nakamura196.github.io/lda2/nagano/manifest/de56bd4685a8d622809972830d673956.json/canvas/p6",
                            "resource": {
                                "@id": "http://www.i-repository.net/il/cont/01/G0000307library/000/148/000148985.jpg",
                                "@type": "dctypes:Image",
                                "format": "image/jpeg",
                                "height": 2016,
                                "width": 3024
                            }
                        }
                    ],
                    "label": "[6]",
                    "thumbnail": {
                        "@id": "http://www.i-repository.net/il/cont/01/G0000307library/000/148/000148985_ls.jpg"
                    },
                    "width": 3024
                },
                {
                    "@id": "https://nakamura196.github.io/lda2/nagano/manifest/de56bd4685a8d622809972830d673956.json/canvas/p7",
                    "@type": "sc:Canvas",
                    "height": 2016,
                    "images": [
                        {
                            "@id": "https://nakamura196.github.io/lda2/nagano/manifest/de56bd4685a8d622809972830d673956.json/annotation/p7-image",
                            "@type": "oa:Annotation",
                            "motivation": "sc:painting",
                            "on": "https://nakamura196.github.io/lda2/nagano/manifest/de56bd4685a8d622809972830d673956.json/canvas/p7",
                            "resource": {
                                "@id": "http://www.i-repository.net/il/cont/01/G0000307library/000/148/000148988.jpg",
                                "@type": "dctypes:Image",
                                "format": "image/jpeg",
                                "height": 2016,
                                "width": 3024
                            }
                        }
                    ],
                    "label": "[7]",
                    "thumbnail": {
                        "@id": "http://www.i-repository.net/il/cont/01/G0000307library/000/148/000148988_ls.jpg"
                    },
                    "width": 3024
                },
                {
                    "@id": "https://nakamura196.github.io/lda2/nagano/manifest/de56bd4685a8d622809972830d673956.json/canvas/p8",
                    "@type": "sc:Canvas",
                    "height": 2016,
                    "images": [
                        {
                            "@id": "https://nakamura196.github.io/lda2/nagano/manifest/de56bd4685a8d622809972830d673956.json/annotation/p8-image",
                            "@type": "oa:Annotation",
                            "motivation": "sc:painting",
                            "on": "https://nakamura196.github.io/lda2/nagano/manifest/de56bd4685a8d622809972830d673956.json/canvas/p8",
                            "resource": {
                                "@id": "http://www.i-repository.net/il/cont/01/G0000307library/000/148/000148989.jpg",
                                "@type": "dctypes:Image",
                                "format": "image/jpeg",
                                "height": 2016,
                                "width": 3024
                            }
                        }
                    ],
                    "label": "[8]",
                    "thumbnail": {
                        "@id": "http://www.i-repository.net/il/cont/01/G0000307library/000/148/000148989_ls.jpg"
                    },
                    "width": 3024
                },
                {
                    "@id": "https://nakamura196.github.io/lda2/nagano/manifest/de56bd4685a8d622809972830d673956.json/canvas/p9",
                    "@type": "sc:Canvas",
                    "height": 2016,
                    "images": [
                        {
                            "@id": "https://nakamura196.github.io/lda2/nagano/manifest/de56bd4685a8d622809972830d673956.json/annotation/p9-image",
                            "@type": "oa:Annotation",
                            "motivation": "sc:painting",
                            "on": "https://nakamura196.github.io/lda2/nagano/manifest/de56bd4685a8d622809972830d673956.json/canvas/p9",
                            "resource": {
                                "@id": "http://www.i-repository.net/il/cont/01/G0000307library/000/148/000148990.jpg",
                                "@type": "dctypes:Image",
                                "format": "image/jpeg",
                                "height": 2016,
                                "width": 3024
                            }
                        }
                    ],
                    "label": "[9]",
                    "thumbnail": {
                        "@id": "http://www.i-repository.net/il/cont/01/G0000307library/000/148/000148990_ls.jpg"
                    },
                    "width": 3024
                },
                {
                    "@id": "https://nakamura196.github.io/lda2/nagano/manifest/de56bd4685a8d622809972830d673956.json/canvas/p10",
                    "@type": "sc:Canvas",
                    "height": 2016,
                    "images": [
                        {
                            "@id": "https://nakamura196.github.io/lda2/nagano/manifest/de56bd4685a8d622809972830d673956.json/annotation/p10-image",
                            "@type": "oa:Annotation",
                            "motivation": "sc:painting",
                            "on": "https://nakamura196.github.io/lda2/nagano/manifest/de56bd4685a8d622809972830d673956.json/canvas/p10",
                            "resource": {
                                "@id": "http://www.i-repository.net/il/cont/01/G0000307library/000/148/000148990.jpg",
                                "@type": "dctypes:Image",
                                "format": "image/jpeg",
                                "height": 2016,
                                "width": 3024
                            }
                        }
                    ],
                    "label": "[10]",
                    "thumbnail": {
                        "@id": "http://www.i-repository.net/il/cont/01/G0000307library/000/148/000148990_ls.jpg"
                    },
                    "width": 3024
                }
            ],
            "label": "Current Page Order",
            "viewingHint": "non-paged"
        }
    ],
    "thumbnail": {
        "@id": "http://www.i-repository.net/il/cont/01/G0000307library/000/148/000148967_ls.jpg"
    },
    "within": "http://www.i-repository.net/il/meta_pub/G0000307library"
}