{
    "@context": "http://iiif.io/api/presentation/2/context.json",
    "@id": "https://nakamura196.github.io/lda2/hokkaido/manifest/49e14f88c494decb471fe9e7467bd3d9.json",
    "@type": "sc:Manifest",
    "attribution": "北方資料デジタル・ライブラリー",
    "label": "佐川町「太刀踊り」公演 平成４年１１月２日 （常呂町）",
    "license": "http://www3.library.pref.hokkaido.jp/digitallibrary/",
    "metadata": [
        {
            "label": "カテゴリー",
            "value": "写真"
        },
        {
            "label": "コンテンツ",
            "value": "ふり返ってみる地域のできごと"
        },
        {
            "label": "タイトル",
            "value": "佐川町「太刀踊り」公演 平成４年１１月２日 （常呂町）"
        },
        {
            "label": "タイトル（ヨミ）",
            "value": "サカワチョウタチオドリコウエン ヘイセイ４ネン１１ガツ２ニチ （トコロチョウ）"
        },
        {
            "label": "所蔵機関",
            "value": "北見市立図書館"
        },
        {
            "label": "管理番号",
            "value": "41305"
        },
        {
            "label": "言語",
            "value": "日本語"
        },
        {
            "label": "館種",
            "value": "公立図書館"
        },
        {
            "label": "説明",
            "value": "「広報ところ」１２月号から：「１０月３１日から１１月４日まで姉妹町の高知県佐川町から訪問団３６人が来町。佐川町に伝わり、３００年の歴史がある「太刀踊り」を３回にわたり公演。勇壮な出で立ちの剣士とシデ紙房という棒を持つ踊り手が交差し、真剣に触れた紙シデが紙吹雪となって飛び散る瞬間は息を呑むほどの迫力」と紹介。"
        }
    ],
    "related": "http://www3.library.pref.hokkaido.jp/digitallibrary/dsearch/da/detail.php?libno=54&data_id=5-41305-1-c1",
    "sequences": [
        {
            "@id": "https://nakamura196.github.io/lda2/hokkaido/manifest/49e14f88c494decb471fe9e7467bd3d9.json/sequence/normal",
            "@type": "sc:Sequence",
            "canvases": [
                {
                    "@id": "https://nakamura196.github.io/lda2/hokkaido/manifest/49e14f88c494decb471fe9e7467bd3d9.json/canvas/p1",
                    "@type": "sc:Canvas",
                    "height": 2000,
                    "images": [
                        {
                            "@id": "https://nakamura196.github.io/lda2/hokkaido/manifest/49e14f88c494decb471fe9e7467bd3d9.json/annotation/p1-image",
                            "@type": "oa:Annotation",
                            "motivation": "sc:painting",
                            "on": "https://nakamura196.github.io/lda2/hokkaido/manifest/49e14f88c494decb471fe9e7467bd3d9.json/canvas/p1",
                            "resource": {
                                "@id": "http://www3.library.pref.hokkaido.jp/digitallibrary/dsearch/ics/viewer/iipsrv.fcgi?FIF=/41305/0261250/0261250_0000001.jp2&WID=full&CVT=jpeg",
                                "@type": "dctypes:Image",
                                "format": "image/jpeg",
                                "height": 2000,
                                "width": 3000
                            }
                        }
                    ],
                    "label": "[1]",
                    "thumbnail": {
                        "@id": "http://www3.library.pref.hokkaido.jp/digitallibrary/dsearch/ics/viewer/iipsrv.fcgi?FIF=/41305/0261250/0261250_0000001.jp2&WID=300&CVT=jpeg"
                    },
                    "width": 3000
                },
                {
                    "@id": "https://nakamura196.github.io/lda2/hokkaido/manifest/49e14f88c494decb471fe9e7467bd3d9.json/canvas/p2",
                    "@type": "sc:Canvas",
                    "height": 2000,
                    "images": [
                        {
                            "@id": "https://nakamura196.github.io/lda2/hokkaido/manifest/49e14f88c494decb471fe9e7467bd3d9.json/annotation/p2-image",
                            "@type": "oa:Annotation",
                            "motivation": "sc:painting",
                            "on": "https://nakamura196.github.io/lda2/hokkaido/manifest/49e14f88c494decb471fe9e7467bd3d9.json/canvas/p2",
                            "resource": {
                                "@id": "http://www3.library.pref.hokkaido.jp/digitallibrary/dsearch/ics/viewer/iipsrv.fcgi?FIF=/41305/0261251/0261251_0000002.jp2&WID=full&CVT=jpeg",
                                "@type": "dctypes:Image",
                                "format": "image/jpeg",
                                "height": 2000,
                                "width": 3000
                            }
                        }
                    ],
                    "label": "[2]",
                    "thumbnail": {
                        "@id": "http://www3.library.pref.hokkaido.jp/digitallibrary/dsearch/ics/viewer/iipsrv.fcgi?FIF=/41305/0261251/0261251_0000002.jp2&WID=300&CVT=jpeg"
                    },
                    "width": 3000
                },
                {
                    "@id": "https://nakamura196.github.io/lda2/hokkaido/manifest/49e14f88c494decb471fe9e7467bd3d9.json/canvas/p3",
                    "@type": "sc:Canvas",
                    "height": 2000,
                    "images": [
                        {
                            "@id": "https://nakamura196.github.io/lda2/hokkaido/manifest/49e14f88c494decb471fe9e7467bd3d9.json/annotation/p3-image",
                            "@type": "oa:Annotation",
                            "motivation": "sc:painting",
                            "on": "https://nakamura196.github.io/lda2/hokkaido/manifest/49e14f88c494decb471fe9e7467bd3d9.json/canvas/p3",
                            "resource": {
                                "@id": "http://www3.library.pref.hokkaido.jp/digitallibrary/dsearch/ics/viewer/iipsrv.fcgi?FIF=/41305/0261252/0261252_0000003.jp2&WID=full&CVT=jpeg",
                                "@type": "dctypes:Image",
                                "format": "image/jpeg",
                                "height": 2000,
                                "width": 3000
                            }
                        }
                    ],
                    "label": "[3]",
                    "thumbnail": {
                        "@id": "http://www3.library.pref.hokkaido.jp/digitallibrary/dsearch/ics/viewer/iipsrv.fcgi?FIF=/41305/0261252/0261252_0000003.jp2&WID=300&CVT=jpeg"
                    },
                    "width": 3000
                },
                {
                    "@id": "https://nakamura196.github.io/lda2/hokkaido/manifest/49e14f88c494decb471fe9e7467bd3d9.json/canvas/p4",
                    "@type": "sc:Canvas",
                    "height": 2000,
                    "images": [
                        {
                            "@id": "https://nakamura196.github.io/lda2/hokkaido/manifest/49e14f88c494decb471fe9e7467bd3d9.json/annotation/p4-image",
                            "@type": "oa:Annotation",
                            "motivation": "sc:painting",
                            "on": "https://nakamura196.github.io/lda2/hokkaido/manifest/49e14f88c494decb471fe9e7467bd3d9.json/canvas/p4",
                            "resource": {
                                "@id": "http://www3.library.pref.hokkaido.jp/digitallibrary/dsearch/ics/viewer/iipsrv.fcgi?FIF=/41305/0261253/0261253_0000004.jp2&WID=full&CVT=jpeg",
                                "@type": "dctypes:Image",
                                "format": "image/jpeg",
                                "height": 2000,
                                "width": 3000
                            }
                        }
                    ],
                    "label": "[4]",
                    "thumbnail": {
                        "@id": "http://www3.library.pref.hokkaido.jp/digitallibrary/dsearch/ics/viewer/iipsrv.fcgi?FIF=/41305/0261253/0261253_0000004.jp2&WID=300&CVT=jpeg"
                    },
                    "width": 3000
                },
                {
                    "@id": "https://nakamura196.github.io/lda2/hokkaido/manifest/49e14f88c494decb471fe9e7467bd3d9.json/canvas/p5",
                    "@type": "sc:Canvas",
                    "height": 2000,
                    "images": [
                        {
                            "@id": "https://nakamura196.github.io/lda2/hokkaido/manifest/49e14f88c494decb471fe9e7467bd3d9.json/annotation/p5-image",
                            "@type": "oa:Annotation",
                            "motivation": "sc:painting",
                            "on": "https://nakamura196.github.io/lda2/hokkaido/manifest/49e14f88c494decb471fe9e7467bd3d9.json/canvas/p5",
                            "resource": {
                                "@id": "http://www3.library.pref.hokkaido.jp/digitallibrary/dsearch/ics/viewer/iipsrv.fcgi?FIF=/41305/0261254/0261254_0000005.jp2&WID=full&CVT=jpeg",
                                "@type": "dctypes:Image",
                                "format": "image/jpeg",
                                "height": 2000,
                                "width": 3000
                            }
                        }
                    ],
                    "label": "[5]",
                    "thumbnail": {
                        "@id": "http://www3.library.pref.hokkaido.jp/digitallibrary/dsearch/ics/viewer/iipsrv.fcgi?FIF=/41305/0261254/0261254_0000005.jp2&WID=300&CVT=jpeg"
                    },
                    "width": 3000
                }
            ],
            "label": "Current Page Order",
            "viewingHint": "non-paged"
        }
    ],
    "thumbnail": {
        "@id": "http://www3.library.pref.hokkaido.jp/digitallibrary/dsearch/ics/viewer/iipsrv.fcgi?FIF=/41305/0261250/0261250_0000001.jp2&WID=300&CVT=jpeg"
    },
    "within": "http://www3.library.pref.hokkaido.jp/digitallibrary/"
}